gcpTokenGenerator.py
gcpTokenGenerator-0.0.2.dist-info/METADATA
gcpTokenGenerator-0.0.2.dist-info/WHEEL
gcpTokenGenerator-0.0.2.dist-info/top_level.txt
gcpTokenGenerator-0.0.2.dist-info/RECORD
