Metadata-Version: 2.1
Name: gcpTokenGenerator
Version: 0.0.2
Summary: google token generator
Author: oribrau@gmail.com
License: MIT
Requires-Dist: requests
Requires-Dist: google-api-python-client
Requires-Dist: oauth2client
